inspirai_fps/__init__.py
inspirai_fps/data_classes.py
inspirai_fps/gamecore.py
inspirai_fps/raycast.py
inspirai_fps/simple_command_pb2.py
inspirai_fps/simple_command_pb2_grpc.py
inspirai_fps/utils.py
inspirai_fps/lib/libraycaster.dll
inspirai_fps/lib/libraycaster.dylib
inspirai_fps/lib/libraycaster.so
inspirai_fps-0.0.3.dist-info/LICENSE
inspirai_fps-0.0.3.dist-info/METADATA
inspirai_fps-0.0.3.dist-info/WHEEL
inspirai_fps-0.0.3.dist-info/top_level.txt
inspirai_fps-0.0.3.dist-info/RECORD
