Metadata-Version: 2.1
Name: inspirai-fps
Version: 0.0.3
Summary: An intelligent agent learning platform based on a 3D open-world FPS game
Home-page: https://github.com/inspirai/wilderness-scavenger
Author: Inspir.AI
Author-email: cog2022@inspirai.com
License: LICENSE
Keywords: inspirai,fps,game,open world,ai,deep learning,reinforcement learning,research
Platform: UNKNOWN
Requires-Python: >=3.8, <4
License-File: LICENSE
Requires-Dist: Pillow
Requires-Dist: numpy
Requires-Dist: grpcio
Requires-Dist: rich
Requires-Dist: protobuf
Requires-Dist: trimesh
Provides-Extra: baseline
Requires-Dist: gym ; extra == 'baseline'
Requires-Dist: ray[rllib] ; extra == 'baseline'
Requires-Dist: torch ; extra == 'baseline'
